loopback/__init__.py
loopback-0.0.2.dist-info/WHEEL
loopback-0.0.2.dist-info/METADATA
loopback-0.0.2.dist-info/RECORD
