Metadata-Version: 2.1
Name: loopback
Version: 0.0.2
Summary: Thread manager and decorator for asynchronous background function execution.
License: MIT
Author: vpuhoff
Author-email: vpuhoff@live.ru
Classifier: License :: OSI Approved :: MIT License
Classifier: Programming Language :: Python :: 2
Classifier: Programming Language :: Python :: 2.7
Classifier: Programming Language :: Python :: 3
Classifier: Programming Language :: Python :: 3.4
Classifier: Programming Language :: Python :: 3.5
Classifier: Programming Language :: Python :: 3.6
Classifier: Programming Language :: Python :: 3.7
